{
    "portfolio": [
        {
            "id": 0,
            "title": "Icon for this website",
            "img": "/res/icon.png",
            "description": "Smoothest bit of graphic design I've made to date.",
            "pixelated": false
        },
        {
            "id": 1,
            "title": "ArmCord Logo",
            "img": "/res/ac_icon.png",
            "description": "The logo I made for ArmCord back in 2021, it's still being used today!|link|https://github.com/ArmCord/ArmCord|link|Here's a link so you could check it out",
            "pixelated": false
        },
        {
            "id": 2,
            "title": "Minimalist SSBU Game Icon",
            "img": "/res/smash.png",
            "description": "I still use this today as my game icon, it looks pretty. :)|link|https://gamebanana.com/mods/460343|link|You can set it as your game icon too",
            "pixelated": false
        },
        {
            "id": 3,
            "title": "stoopid",
            "img": "/res/Untitled-1.png",
            "description": "dumb stinky",
            "pixelated": true
        },
        {
            "id": 4,
            "title": "what gta does to young children (100% true)",
            "img": "/res/violence.png",
            "description": "THE BABY HAS A GUN!!!",
            "pixelated": true
        },
        {
            "id": 5,
            "title": "Greyscale Ness Render",
            "img": "/res/finished.png",
            "description": "My first notable attempt at using Blender. (Still used Photoshop for a few touchups)|link|https://gamebanana.com/mods/396920|link|Check out the mod!"
        },
        {
            "id": 6,
            "title": "Minecraft Rerendered Final Logo",
            "img": "/res/rerenderderder.png",
            "description": "A logo I made in a few minutes for a mod that took me a few years.|link|https://gamebanana.com/mods/27569|link|Check it out!",
            "pixelated": false
        },
        {
            "id": 7,
            "title": "Steve Rerendered",
            "img": "/res/RendaSteve00.png",
            "description": "This was made using a mix of Mine-imator and Photopea, for fake lighting.|link|https://gamebanana.com/mods/27569|link|Check out the mod!",
            "pixelated": false
        },
        {
            "id": 8,
            "title": "@infinite_bugz Minecraft Skin",
            "img": "/res/inf_shot_pub.png",
            "description": "A Minecraft skin I made for a friend of mine.|link|https://www.instagram.com/infinite_bugz|link|Check em out on Instagram!",
            "pixelated": false
        },
        {
            "id": 9,
            "title": "My Minecraft Skin",
            "img": "/res/kck_mc-skin.png",
            "description": "My personal Minecraft skin, I'm proud of this one!",
            "pixelated": false
        },
        {
            "id": 10,
            "title": "Upgraded Frisk Spritesheet",
            "img": "/res/frisky.png",
            "description": "Fun little thing I made :3",
            "pixelated": false
        },
        {
            "id": 11,
            "title": "Upgraded Chara Spritesheet",
            "img": "/res/character.png",
            "description": "Yet another fun little thing I made :)",
            "pixelated": false
        },
        {
            "id": 12,
            "title": "Upgraded Frisk Spritesheet",
            "img": "/res/frisky_fanon.png",
            "description": "A varient of one of the fun little things I made :3",
            "pixelated": false
        }
    ],
    "projects": [
        {
            "icon": "https://raw.githubusercontent.com/kckarnige/OculusDummy/main/icon.png",
            "name": "Oculus Dummy",
            "description": "Oculus Killer, but for the Oculus Client.",
            "link": "https://github.com/kckarnige/OculusDummy",
            "textColor": "#fff",
            "background": "linear-gradient(to bottom right, rgb(13, 17, 37), rgb(38, 14, 28))"
        },
        {
            "icon": "https://raw.githubusercontent.com/kckarnige/OculusKillSwitch/main/icon-dark.png",
            "name": "Oculus Kill Switch",
            "description": "Toggle Oculus Killer and play your Oculus games how Zuck intended.",
            "link": "https://github.com/kckarnige/OculusKillSwitch",
            "textColor": "#fff",
            "background": "linear-gradient(to bottom right, rgb(13, 17, 37), rgb(38, 14, 28))"
        },
        {
            "icon": "https://raw.githubusercontent.com/kckarnige/EcstaTab/main/src/res/icons/white-256.png",
            "name": "Ecsta",
            "description": "A simple new tab extension meant to stay out of your way while still making for great eye-candy.",
            "link": "https://github.com/kckarnige/EcstaTab",
            "textColor": "#fff",
            "background": "linear-gradient(to bottom right, rgb(1, 222, 219), rgb(30, 135, 253))"
        },
        {
            "icon": "/res/fug-igg.png",
            "name": "FUG IGG",
            "description": "Fast Url Generator for IGG-games.com, because why wait to install cryptominers?",
            "link": "https://gist.github.com/kckarnige/6dfff1025b5da69399c26957ee47b445",
            "textColor": "#fff",
            "background": "linear-gradient(to bottom right, rgb(75, 124, 143), rgb(58, 91, 88))"
        },
        {
            "icon": "/res/a.png",
            "name": "Greyscale Ness",
            "description": "''Finally, Dark Ness'' -CaptainDragon636",
            "link": "https://gamebanana.com/mods/396920",
            "textColor": "#d14b48",
            "background": "linear-gradient(to bottom right, #3d3d3d, #1d1d1d)"
        },
        {
            "icon": "/res/rerenderderder.png",
            "name": "Minecraft Rerendered",
            "description": "Actually Smashifies the Minecraft renders.",
            "link": "https://gamebanana.com/mods/27569",
            "textColor": "#fff",
            "background": "url(/res/mc_back.png)"
        },
        {
            "icon": "/res/fuck.png",
            "name": "Consistent Netherite",
            "description": "Makes Netherite tools fit-in more, while still being unique.",
            "link": "https://modrinth.com/resourcepack/consistent-netherite",
            "textColor": "#231012",
            "background": "url(/res/invert-slate.png)"
        },
        {
            "icon": "/res/tscm-icon_justlogo.png",
            "name": "Subjectively Correct",
            "description": "A modpack that aims to make Minecraft feel better, in my subjective opinion.",
            "link": "https://modrinth.com/modpack/tscm",
            "textColor": "#fff",
            "background": "url(/res/tscm_back.png)"
        }
    ]
}